reducelib/__init__.py
reducelib/reducelib.py
reducelib-0.1.1.dist-info/METADATA
reducelib-0.1.1.dist-info/WHEEL
reducelib-0.1.1.dist-info/RECORD
